modelflows/__init__.py
modelflows/config.py
modelflows/emulator.py
modelflows/likelihoods.py
modelflows/sampler.py
modelflows/utils.py
modelflows/version.py
modelflows/data/scaler/cnfdwarf_d01.scaler
modelflows/data/scaler/cnfdwarf_mms_core.scaler
modelflows/data/scaler/cnfdwarf_mms_shell.scaler
modelflows/data/scaler/cnfdwarf_teff.scaler
modelflows/data/scaler/cnfgiant_d01.scaler
modelflows/data/scaler/cnfgiant_mms_core.scaler
modelflows/data/scaler/cnfgiant_mms_shell.scaler
modelflows/data/scaler/cnfgiant_teff.scaler
modelflows-0.0.2.dist-info/LICENSE
modelflows-0.0.2.dist-info/METADATA
modelflows-0.0.2.dist-info/WHEEL
modelflows-0.0.2.dist-info/top_level.txt
modelflows-0.0.2.dist-info/RECORD
