Metadata-Version: 2.1
Name: modelflows
Version: 0.0.2
Summary: Conditional normalizing flows for emulating grids of stellar models
Home-page: https://github.com/mtyhon/modelflows
Author: Marc Hon
License: MIT
License-File: LICENSE
Requires-Dist: numpy
Requires-Dist: scipy
Requires-Dist: pandas
Requires-Dist: tqdm
Requires-Dist: corner
Requires-Dist: matplotlib
Requires-Dist: torch >=2.0.0
Requires-Dist: scikit-learn >=1.3.0
Requires-Dist: arviz >=0.12.1
Requires-Dist: zuko ==0.3.2
